pydasa/__init__.py
pydasa/_version.py
pydasa/analysis/__init__.py
pydasa/analysis/scenario.py
pydasa/analysis/simulation.py
pydasa/context/__init__.py
pydasa/context/conversion.py
pydasa/context/system.py
pydasa/context/units.py
pydasa/core/__init__.py
pydasa/core/basic.py
pydasa/core/constants.py
pydasa/core/io.py
pydasa/core/setup.py
pydasa/core/cfg/default.json
pydasa/dimensional/__init__.py
pydasa/dimensional/buckingham.py
pydasa/dimensional/fundamental.py
pydasa/dimensional/model.py
pydasa/dimensional/vaschy.py
pydasa/elements/__init__.py
pydasa/elements/parameter.py
pydasa/elements/specs/__init__.py
pydasa/elements/specs/conceptual.py
pydasa/elements/specs/numerical.py
pydasa/elements/specs/statistical.py
pydasa/elements/specs/symbolic.py
pydasa/serialization/__init__.py
pydasa/serialization/parser.py
pydasa/structs/__init__.py
pydasa/structs/lists/__init__.py
pydasa/structs/lists/arlt.py
pydasa/structs/lists/dllt.py
pydasa/structs/lists/ndlt.py
pydasa/structs/lists/sllt.py
pydasa/structs/tables/__init__.py
pydasa/structs/tables/htme.py
pydasa/structs/tables/scht.py
pydasa/structs/tools/__init__.py
pydasa/structs/tools/hashing.py
pydasa/structs/tools/math.py
pydasa/structs/tools/memory.py
pydasa/structs/types/__init__.py
pydasa/structs/types/functions.py
pydasa/structs/types/generics.py
pydasa/validations/__init__.py
pydasa/validations/decorators.py
pydasa/validations/error.py
pydasa/validations/patterns.py
pydasa/workflows/__init__.py
pydasa/workflows/basic.py
pydasa/workflows/influence.py
pydasa/workflows/phenomena.py
pydasa/workflows/practical.py
pydasa-0.6.4.dist-info/licenses/LICENSE
pydasa-0.6.4.dist-info/METADATA
pydasa-0.6.4.dist-info/WHEEL
pydasa-0.6.4.dist-info/top_level.txt
pydasa-0.6.4.dist-info/RECORD
