Metadata-Version: 2.4
Name: pydasa
Version: 0.6.4
Summary: Python package for Dimensional Analysis for Scientific Applications and Software Architecture (PyDASA).
Home-page: https://github.com/DASA-Design/PyDASA
Author: @SFAM
Author-email: "@SFAM" <sa-artea@uniandes.edu.co>
License-Expression: GPL-3.0-or-later
Project-URL: Homepage, https://github.com/DASA-Design/PyDASA
Classifier: Programming Language :: Python :: 3.10
Classifier: Programming Language :: Python :: 3.11
Classifier: Programming Language :: Python :: 3.12
Classifier: Development Status :: 3 - Alpha
Classifier: Operating System :: OS Independent
Classifier: Intended Audience :: Science/Research
Classifier: Intended Audience :: Developers
Classifier: Topic :: Scientific/Engineering
Requires-Python: >=3.10
License-File: LICENSE
Requires-Dist: antlr4-python3-runtime==4.11
Requires-Dist: numpy>=1.26.4
Requires-Dist: scipy>=1.13.0
Requires-Dist: sympy>=1.12
Requires-Dist: matplotlib>=3.8.0
Requires-Dist: pandas>=2.1.0
Requires-Dist: SALib>=1.4.5
Provides-Extra: dev
Requires-Dist: pytest>=8.1.1; extra == "dev"
Requires-Dist: twine>=6.1.0; extra == "dev"
Provides-Extra: docs
Requires-Dist: sphinx>=7.3.7; extra == "docs"
Requires-Dist: pydata-sphinx-theme>=0.14.0; extra == "docs"
Requires-Dist: sphinx-autodoc-typehints>=1.24.0; extra == "docs"
Requires-Dist: sphinx-autoapi>=3.0.0; extra == "docs"
Requires-Dist: myst-parser>=2.0.0; extra == "docs"
Requires-Dist: sphinx-copybutton>=0.5.2; extra == "docs"
Requires-Dist: sphinx-favicon>=1.0.1; extra == "docs"
Requires-Dist: sphinx-gitstamp>=0.3.3; extra == "docs"
Requires-Dist: sphinx-prompt>=1.8.0; extra == "docs"
Requires-Dist: sphinx-markdown-builder>=0.6.5; extra == "docs"
Requires-Dist: myst-parser>=2.0.0; extra == "docs"
Requires-Dist: nbsphinx>=0.9.0; extra == "docs"
Dynamic: author
Dynamic: home-page
Dynamic: license-file
Dynamic: requires-python
